<?xml version="1.0"?>
<!DOCTYPE hibernate-mapping PUBLIC "-//Hibernate/Hibernate Mapping DTD 3.0//EN"
"http://hibernate.sourceforge.net/hibernate-mapping-3.0.dtd">
<!-- Generated Apr 7, 2014 9:39:14 PM by Hibernate Tools 3.4.0.CR1 -->
<hibernate-mapping>
    <class name="org.motechproject.batch.model.BatchJobExecutionParams" table="batch_job_execution_params" schema="batch">
        <id name="jobExecutionParamsId" type="long">
            <column name="job_execution_params_id" />
            <generator class="assigned" />
        </id>
        <property name="jobExecutionId" type="long">
            <column name="job_execution_id" not-null="true" />
        </property>
        <property name="typeCd" type="string">
            <column name="type_cd" length="6" not-null="true" />
        </property>
        <property name="keyName" type="string">
            <column name="key_name" length="100" not-null="true" />
        </property>
        <property name="stringVal" type="string">
            <column name="string_val" length="250" />
        </property>
        <property name="dateVal" type="timestamp">
            <column name="date_val" length="29" />
        </property>
        <property name="longVal" type="java.lang.Long">
            <column name="long_val" />
        </property>
        <property name="doubleVal" type="java.lang.Double">
            <column name="double_val" precision="17" scale="17" />
        </property>
        <property name="identifying" type="char">
            <column name="identifying" length="1" not-null="true" />
        </property>
        <property name="createdBy" type="string">
            <column name="created_by" length="15" />
        </property>
        <property name="lastUpdatedBy" type="string">
            <column name="last_updated_by" length="15" />
        </property>
    </class>
</hibernate-mapping>
